odoo8_addon_hr_payslip_change_state-8.0.1.0.0-py2.7-nspkg.pth
odoo_addons/hr_payslip_change_state/__openerp__.py
odoo_addons/hr_payslip_change_state/__init__.py
odoo_addons/hr_payslip_change_state/README.rst
odoo_addons/hr_payslip_change_state/wizard/hr_payslip_change_state.py
odoo_addons/hr_payslip_change_state/wizard/__init__.py
odoo_addons/hr_payslip_change_state/wizard/hr_payslip_change_state_view.xml
odoo_addons/hr_payslip_change_state/tests/test_hr_payslip_change_state.py
odoo_addons/hr_payslip_change_state/tests/__init__.py
odoo8_addon_hr_payslip_change_state-8.0.1.0.0.dist-info/top_level.txt
odoo8_addon_hr_payslip_change_state-8.0.1.0.0.dist-info/WHEEL
odoo8_addon_hr_payslip_change_state-8.0.1.0.0.dist-info/RECORD
odoo8_addon_hr_payslip_change_state-8.0.1.0.0.dist-info/metadata.json
odoo8_addon_hr_payslip_change_state-8.0.1.0.0.dist-info/DESCRIPTION.rst
odoo8_addon_hr_payslip_change_state-8.0.1.0.0.dist-info/METADATA
odoo8_addon_hr_payslip_change_state-8.0.1.0.0.dist-info/namespace_packages.txt
