Metadata-Version: 2.0
Name: odoo8-addon-hr-payslip-change-state
Version: 8.0.1.0.0
Summary: Change the state of many payslips at a time
Home-page: UNKNOWN
Author: Eficent, Odoo Community Association (OCA)
Author-email: support@odoo-community.org
License: AGPL-3
Platform: UNKNOWN
Requires-Dist: odoo (<9.0a,>=8.0a)
Requires-Dist: odoo8-addon-hr-payroll-cancel
Classifier: Programming Language :: Python :: 2.7
Classifier: Framework :: Odoo
Classifier: License :: OSI Approved :: GNU Affero General Public License v3
